mknsmPy/__init__.py
mknsmPy/mknsmPy.py
mknsmPy-0.3.dist-info/LICENSE
mknsmPy-0.3.dist-info/METADATA
mknsmPy-0.3.dist-info/WHEEL
mknsmPy-0.3.dist-info/top_level.txt
mknsmPy-0.3.dist-info/RECORD
