Metadata-Version: 2.1
Name: mknsmPy
Version: 0.3
Summary: mekanism material calculator
Home-page: https://github.com/hihimamuLab/MekanismCalcLibrary.git
Author: hihimamu
Author-email: mamu.pypi@shchiba.uk
License: MIT
Keywords: mekanism,mechanism,mknsm,mknsmPy
License-File: LICENSE
